balanced_kmeans
