Metadata-Version: 2.1
Name: balanced-kmeans
Version: 0.0.7
Summary: Balanced kmeans with cuda support in Pytorch.
Home-page: https://github.com/giannisdaras/balanced_kmeans
Author: @giannisdaras
Author-email: daras.giannhs@gmail.com
License: License :: OSI Approved :: MIT License
Platform: UNKNOWN
Classifier: Programming Language :: Python :: 3
Requires-Python: >=3.6
